{
    "tweets": [
        {
            "edit_history_tweet_ids": [
                1598656598771372033
            ],
            "id": 1598656598771372033,
            "text": "いちご青汁ラテと畑で採れた野菜のスムージー野菜を添えて🤔"
        },
        {
            "edit_history_tweet_ids": [
                1598656544870387714
            ],
            "id": 1598656544870387714,
            "text": "【いちご青汁ラテ】が【毒汁】に見えたのよね(あながち間違いではない…味的に…知らんけど)"
        },
        {
            "edit_history_tweet_ids": [
                1598656521352933376
            ],
            "id": 1598656521352933376,
            "text": "いちご青汁ラテ何事。。。❔って思ったら刀剣じゃないですか。。。"
        },
        {
            "edit_history_tweet_ids": [
                1598656465442836481
            ],
            "id": 1598656465442836481,
            "text": "いちご青汁ラテ"
        },
        {
            "edit_history_tweet_ids": [
                1598656436057559041
            ],
            "id": 1598656436057559041,
            "text": "いちご青汁ラテって何だよ"
        },
        {
            "edit_history_tweet_ids": [
                1598656393187557376
            ],
            "id": 1598656393187557376,
            "text": "いちご青汁ラテ………？？？"
        },
        {
            "edit_history_tweet_ids": [
                1598656338833571840
            ],
            "id": 1598656338833571840,
            "text": "RT @_mochi2_mochi: トレンドの『いちご青汁ラテ』(豊前江)\n\nえー、と思ったけど子供向けで存在している。混ぜればコレって事で良いのかな… https://t.co/PlZdXGhNNx"
        },
        {
            "edit_history_tweet_ids": [
                1598656334375051264
            ],
            "id": 1598656334375051264,
            "text": "いちご青汁ラテ…………？？\nと思ったらあの方ですか…………\n豊前＝いちご青汁ラテでおーけー？(違う)"
        },
        {
            "edit_history_tweet_ids": [
                1598656309443760128
            ],
            "id": 1598656309443760128,
            "text": "いちご青汁ラテ……？？？？？？？？？？？？？？？？？？？？？？？？"
        },
        {
            "edit_history_tweet_ids": [
                1598656289445675008
            ],
            "id": 1598656289445675008,
            "text": "トレンドのいちご青汁ラテ、一体どこのどいつだそんなトンチキな飲み物出すやつはと思ったら豊前江wwwwwしぬwwwwww"
        },
        {
            "edit_history_tweet_ids": [
                1598656269833105408
            ],
            "id": 1598656269833105408,
            "text": "いちご青汁ラテ…？"
        },
        {
            "edit_history_tweet_ids": [
                1598656196248244230
            ],
            "id": 1598656196248244230,
            "text": "豊前さんのドリンク、よもぎ→抹茶ミルク→メロンソーダと来て次はいちご青汁ラテか…メロンソーダからの振り幅でかいな\nコラボカフェで青汁提供するのって結構珍しくない？"
        },
        {
            "edit_history_tweet_ids": [
                1598656191282184192
            ],
            "id": 1598656191282184192,
            "text": "これかあ、いちご青汁ラテ……（にっこり）\nりいだあの味覚アレ疑惑がますます…………………"
        },
        {
            "edit_history_tweet_ids": [
                1598656135460179968
            ],
            "id": 1598656135460179968,
            "text": "メニューの名前で思ったこと。\nうちら世代が定年退職したあとに、インスタ映えで飲んでそうなラインナップw\n\nいちご青汁ラテとか🤭🤭彩りの良いがっつり和食のお弁当とか🤭🤭🤭 https://t.co/BHzaTJDXVC"
        },
        {
            "edit_history_tweet_ids": [
                1598656058297581568
            ],
            "id": 1598656058297581568,
            "text": "いちご青汁ラテとは\n何ぞやと思ったら\n刀剣乱舞のカフェのやつか…"
        },
        {
            "edit_history_tweet_ids": [
                1598655999291711488
            ],
            "id": 1598655999291711488,
            "text": "いちご青汁ラテこれか"
        },
        {
            "edit_history_tweet_ids": [
                1598655969935863808
            ],
            "id": 1598655969935863808,
            "text": "RT @sakuhi0209: いちご青汁ラテって何って思ったら自ジャンルなのクソ笑ったけど\nもう一個もまぁまぁすごい https://t.co/V0a6o0iz18"
        },
        {
            "edit_history_tweet_ids": [
                1598655941855305728
            ],
            "id": 1598655941855305728,
            "text": "…え？トレンドのいちご青汁ラテが気になってタップしたら…え？刀剣???\nはぁ？？ https://t.co/0du85PAMVm"
        },
        {
            "edit_history_tweet_ids": [
                1598655916546875392
            ],
            "id": 1598655916546875392,
            "text": "RT @K_arashi: トレンドにいちご青汁ラテがあって「何だこの未知の飲み物は……」って戦々恐々しながら見たら自ジャンルだった時の私の気持ち"
        },
        {
            "edit_history_tweet_ids": [
                1598655888486977536
            ],
            "id": 1598655888486977536,
            "text": "いちご青汁ラテ…？？"
        },
        {
            "edit_history_tweet_ids": [
                1598655849320550401
            ],
            "id": 1598655849320550401,
            "text": "トレンドのいちご青汁ラテ何？？って思ったら刀で豊前で草"
        },
        {
            "edit_history_tweet_ids": [
                1598655782702428161
            ],
            "id": 1598655782702428161,
            "text": "いちご青汁ラテなに？って思ったらカフェか チョコプロテインに青汁入れて牛乳で飲んでた人間だから普通に思えてしまう"
        },
        {
            "edit_history_tweet_ids": [
                1598655762896588801
            ],
            "id": 1598655762896588801,
            "text": "RT @kinaco_328: 正直豊前のいちご青汁ラテより桑名の畑で採れた野菜のスムージー野菜を添えての方が怖くない？野菜ってことしかわからんよ？ https://t.co/eAtUvAqu2H"
        },
        {
            "edit_history_tweet_ids": [
                1598655732685017088
            ],
            "id": 1598655732685017088,
            "text": "RT @K_arashi: トレンドにいちご青汁ラテがあって「何だこの未知の飲み物は……」って戦々恐々しながら見たら自ジャンルだった時の私の気持ち"
        },
        {
            "edit_history_tweet_ids": [
                1598655702527975424
            ],
            "id": 1598655702527975424,
            "text": "RT @fuhihinohito: 殺伐としたTLにいちご青汁ラテが https://t.co/kp8XBrV60D"
        },
        {
            "edit_history_tweet_ids": [
                1598655680785055744
            ],
            "id": 1598655680785055744,
            "text": "いちご青汁ラテ いちご青汁ラテ？？？？"
        },
        {
            "edit_history_tweet_ids": [
                1598655663135129600
            ],
            "id": 1598655663135129600,
            "text": "いちご…青汁…ラテ……？？？\nわたしたちは試されていますか？？？"
        },
        {
            "edit_history_tweet_ids": [
                1598655534953299968
            ],
            "id": 1598655534953299968,
            "text": "「いちご青汁ラテ」がトレンドに上がってたから罰ゲームか何かか？食べ物で遊ぶなと思ってたら、刀剣乱舞だった"
        },
        {
            "edit_history_tweet_ids": [
                1598655498727088128
            ],
            "id": 1598655498727088128,
            "text": "いちご青汁ラテ何かと思ったら豊前で草"
        },
        {
            "edit_history_tweet_ids": [
                1598655458654711809
            ],
            "id": 1598655458654711809,
            "text": "豊前江のいちご青汁ラテもやばいが桑名江の「野菜のスムージー 野菜を添えて」もなかなか…せめて入ってる野菜の名称を教えてくれ…江お前らそうゆう所あるよなそんな君達が好きだぞ😌"
        },
        {
            "edit_history_tweet_ids": [
                1598655435158192130
            ],
            "id": 1598655435158192130,
            "text": "いちご青汁ラテは意外にいけると思うんだよね\n青汁って牛乳に溶かすよね？？\n苺だけが未知数"
        },
        {
            "edit_history_tweet_ids": [
                1598655424487882753
            ],
            "id": 1598655424487882753,
            "text": "いちご青汁ラテこれかぁ…"
        },
        {
            "edit_history_tweet_ids": [
                1598655356892499969
            ],
            "id": 1598655356892499969,
            "text": "待て、いちご青汁ラテもあるな……"
        },
        {
            "edit_history_tweet_ids": [
                1598655351607463938
            ],
            "id": 1598655351607463938,
            "text": "いちご青汁ラテってどんな気持ちで飲めばいいの"
        },
        {
            "edit_history_tweet_ids": [
                1598655282045153280
            ],
            "id": 1598655282045153280,
            "text": "いちご青汁ラテ…？？？？？？？？？？"
        },
        {
            "edit_history_tweet_ids": [
                1598655261635661824
            ],
            "id": 1598655261635661824,
            "text": "い、いちご青汁ラテ…！？"
        },
        {
            "edit_history_tweet_ids": [
                1598655155997904896
            ],
            "id": 1598655155997904896,
            "text": "いちご……青汁ラテ ??????? https://t.co/DZVGA0uFxz"
        },
        {
            "edit_history_tweet_ids": [
                1598655133340270593
            ],
            "id": 1598655133340270593,
            "text": "いちご青汁ラテ…？って思ったら刀剣か。"
        },
        {
            "edit_history_tweet_ids": [
                1598655119108997120
            ],
            "id": 1598655119108997120,
            "text": "いちご青汁ラテ…？"
        },
        {
            "edit_history_tweet_ids": [
                1598655104764157952
            ],
            "id": 1598655104764157952,
            "text": "RT @K_arashi: トレンドにいちご青汁ラテがあって「何だこの未知の飲み物は……」って戦々恐々しながら見たら自ジャンルだった時の私の気持ち"
        },
        {
            "edit_history_tweet_ids": [
                1598655000808677376
            ],
            "id": 1598655000808677376,
            "text": "RT @K_arashi: トレンドにいちご青汁ラテがあって「何だこの未知の飲み物は……」って戦々恐々しながら見たら自ジャンルだった時の私の気持ち"
        },
        {
            "edit_history_tweet_ids": [
                1598654959427342337
            ],
            "id": 1598654959427342337,
            "text": "いちご青汁ラテwww声出して笑うわこんなん\n\nやべえな豊前江本編でもネタにしてくれ"
        },
        {
            "edit_history_tweet_ids": [
                1598654945598664705
            ],
            "id": 1598654945598664705,
            "text": "いちご青汁ラテなんてトンチキなもん出したのどこかと思ったらとうらぶで笑ったし豊前江でもっと笑った"
        },
        {
            "edit_history_tweet_ids": [
                1598654940683341825
            ],
            "id": 1598654940683341825,
            "text": "いちご青汁ラテ……？"
        },
        {
            "edit_history_tweet_ids": [
                1598654835888631808
            ],
            "id": 1598654835888631808,
            "text": "いちご青汁ラテ、変なコラボメニューか？と思ったらその通りだったし豊前江だった　あんたかよ"
        },
        {
            "edit_history_tweet_ids": [
                1598654764744835072
            ],
            "id": 1598654764744835072,
            "text": "いちご青汁ラテwwwww"
        },
        {
            "edit_history_tweet_ids": [
                1598654725012217858
            ],
            "id": 1598654725012217858,
            "text": "いちご青汁ラテ、、、、、？\nおいしい、、のか、、、？"
        },
        {
            "edit_history_tweet_ids": [
                1598654710646726656
            ],
            "id": 1598654710646726656,
            "text": "いちご青汁ラテ………"
        },
        {
            "edit_history_tweet_ids": [
                1598654704988610560
            ],
            "id": 1598654704988610560,
            "text": "いちご青汁ラテw美味しそうやからホットティラミスラテにばっかり目が行ってたわw"
        },
        {
            "edit_history_tweet_ids": [
                1598654697409499137
            ],
            "id": 1598654697409499137,
            "text": "いちご青汁ラテってなんだ…またあんスタ、アイナナ、にじさんじあたりがやべーもん生み出したのか？(偏見)って思ったら自界隈だった話していい？\n\nとうらぶくんさぁ…"
        },
        {
            "edit_history_tweet_ids": [
                1598654654958931970
            ],
            "id": 1598654654958931970,
            "text": "よそから流れてきたけど、他のメニュー普通なのにあなた(いちご青汁ラテ) だけどうして？ https://t.co/EvfAYyy0Mj"
        },
        {
            "edit_history_tweet_ids": [
                1598654622423744514
            ],
            "id": 1598654622423744514,
            "text": "RT @K_arashi: トレンドにいちご青汁ラテがあって「何だこの未知の飲み物は……」って戦々恐々しながら見たら自ジャンルだった時の私の気持ち"
        },
        {
            "edit_history_tweet_ids": [
                1598654589246607361
            ],
            "id": 1598654589246607361,
            "text": "いちご青汁ラテ……？？"
        },
        {
            "edit_history_tweet_ids": [
                1598654483629998080
            ],
            "id": 1598654483629998080,
            "text": "RT @K_arashi: トレンドにいちご青汁ラテがあって「何だこの未知の飲み物は……」って戦々恐々しながら見たら自ジャンルだった時の私の気持ち"
        },
        {
            "edit_history_tweet_ids": [
                1598654480043888640
            ],
            "id": 1598654480043888640,
            "text": "RT @K_arashi: トレンドにいちご青汁ラテがあって「何だこの未知の飲み物は……」って戦々恐々しながら見たら自ジャンルだった時の私の気持ち"
        },
        {
            "edit_history_tweet_ids": [
                1598654475182669825
            ],
            "id": 1598654475182669825,
            "text": "いちご青汁ラテって美味しいの...?"
        },
        {
            "edit_history_tweet_ids": [
                1598654464344600576
            ],
            "id": 1598654464344600576,
            "text": "RT @K_arashi: トレンドにいちご青汁ラテがあって「何だこの未知の飲み物は……」って戦々恐々しながら見たら自ジャンルだった時の私の気持ち"
        },
        {
            "edit_history_tweet_ids": [
                1598654463967137792
            ],
            "id": 1598654463967137792,
            "text": "いちご青汁ラテは個人的にまだわかる\n青汁の粉末、オレンジジュースで溶いたら飲めるしその感じやろ\nだが野菜スムージーに何故野菜を添えたんだ桑名"
        },
        {
            "edit_history_tweet_ids": [
                1598654316487008256
            ],
            "id": 1598654316487008256,
            "text": "僕最近、健康診断で引っかかってマミーから青汁飲むといいよって言われてるから豊前ニキのいちご青汁ラテいいじゃんと思ったけどいちごだしクリームたっぷり乗ってるし健康…？ #とうらぶ"
        },
        {
            "edit_history_tweet_ids": [
                1598654164560535552
            ],
            "id": 1598654164560535552,
            "text": "RT @hdiwja_0713: ちが！違うんです！！！\n豊前くんの「いちご青汁ラテ｣は\n”彼が甘いだけじゃなくて苦味を兼ね備えてる”っていう公式からの解釈なんです…‼️‼️‼️\n\n豊前くんも「やりてぇことやれば良い｣って言ってたもんな‼️‼️ https://t.co/KTC…"
        },
        {
            "edit_history_tweet_ids": [
                1598654110496362500
            ],
            "id": 1598654110496362500,
            "text": "いちご青汁ラテと野菜スムージー(野菜添え)が頭抜けて2大トンチキなせいで、ラムネミルクがマシに見える……いや限りなく普通に近い……？(大混乱)"
        },
        {
            "edit_history_tweet_ids": [
                1598654060730929158
            ],
            "id": 1598654060730929158,
            "text": "いちご青汁ラテちょっと気になる"
        },
        {
            "edit_history_tweet_ids": [
                1598654060198264832
            ],
            "id": 1598654060198264832,
            "text": "いちご青汁ラテとかスタバえぐって思ってたら某刀ジャンルの某すきぴで笑う"
        },
        {
            "edit_history_tweet_ids": [
                1598654059682353153
            ],
            "id": 1598654059682353153,
            "text": "いちご青汁ラテってオモロすぎるよ"
        },
        {
            "edit_history_tweet_ids": [
                1598653993903083520
            ],
            "id": 1598653993903083520,
            "text": "いちご青汁ラテ……生の苺って青臭いこともあるのでけっこうアリな気もするんだけど、それはそれとして青汁が低解像度だと毒汁に見えてぎょっとした……"
        },
        {
            "edit_history_tweet_ids": [
                1598653974290522112
            ],
            "id": 1598653974290522112,
            "text": "いちご青汁ラテ🤔🤔🤔🤔🤔🤔🤔\nい、え、なんて？？？？いちご青汁ラテ🤔🤔🤔🤔？？？？？？？"
        },
        {
            "edit_history_tweet_ids": [
                1598653898532610048
            ],
            "id": 1598653898532610048,
            "text": "いちご青汁ラテってなに。。。？"
        },
        {
            "edit_history_tweet_ids": [
                1598653856543539206
            ],
            "id": 1598653856543539206,
            "text": "にごカフェ全く興味なかったけど俄然飲んでみたいじゃんいちご青汁ラテ……"
        },
        {
            "edit_history_tweet_ids": [
                1598653843885416448
            ],
            "id": 1598653843885416448,
            "text": "RT @kinaco_328: 正直豊前のいちご青汁ラテより桑名の畑で採れた野菜のスムージー野菜を添えての方が怖くない？野菜ってことしかわからんよ？ https://t.co/eAtUvAqu2H"
        },
        {
            "edit_history_tweet_ids": [
                1598653810729443328
            ],
            "id": 1598653810729443328,
            "text": "みんなもも歌で刀ミュみて彼氏の擬人化と評される豊前江にメロったあとこのメニューみてほしい　いちご青汁ラテ"
        },
        {
            "edit_history_tweet_ids": [
                1598653735789817856
            ],
            "id": 1598653735789817856,
            "text": "RT @fuhihinohito: 殺伐としたTLにいちご青汁ラテが https://t.co/kp8XBrV60D"
        },
        {
            "edit_history_tweet_ids": [
                1598653707456983042
            ],
            "id": 1598653707456983042,
            "text": "いちご青汁ラテ…🤔"
        },
        {
            "edit_history_tweet_ids": [
                1598653704244428806
            ],
            "id": 1598653704244428806,
            "text": "いちご青汁ラテ以外も頼むの勇気いる"
        },
        {
            "edit_history_tweet_ids": [
                1598653616767705088
            ],
            "id": 1598653616767705088,
            "text": "いちご青汁ラテ…豊前…難解なキャラよ…。"
        },
        {
            "edit_history_tweet_ids": [
                1598653559469662209
            ],
            "id": 1598653559469662209,
            "text": "RT @fuhihinohito: 殺伐としたTLにいちご青汁ラテが https://t.co/kp8XBrV60D"
        },
        {
            "edit_history_tweet_ids": [
                1598653536417746949
            ],
            "id": 1598653536417746949,
            "text": "トレンドのいちご青汁ラテてなんよと思ったらまさかのりいだあだった\n\n気狂いですか？"
        },
        {
            "edit_history_tweet_ids": [
                1598653523347898368
            ],
            "id": 1598653523347898368,
            "text": "いちご青汁ラテ…？？？？？ https://t.co/SSUNC49XJp"
        },
        {
            "edit_history_tweet_ids": [
                1598653518013173760
            ],
            "id": 1598653518013173760,
            "text": "いちご青汁ラテ…？？"
        },
        {
            "edit_history_tweet_ids": [
                1598653498337685505
            ],
            "id": 1598653498337685505,
            "text": "ちょ まて いちご青汁ラテにかすんでっけどテイクアウトお前ぇぇぇ！！！！お前も青汁か！！！！！(°-°)ｶｯ"
        },
        {
            "edit_history_tweet_ids": [
                1598653495032582146
            ],
            "id": 1598653495032582146,
            "text": "RT @K_arashi: トレンドにいちご青汁ラテがあって「何だこの未知の飲み物は……」って戦々恐々しながら見たら自ジャンルだった時の私の気持ち"
        },
        {
            "edit_history_tweet_ids": [
                1598653442129813504
            ],
            "id": 1598653442129813504,
            "text": "いちご青汁ラテ🍓\nなんとなく味の想像はつかんこともないけれども……でもどうして……"
        },
        {
            "edit_history_tweet_ids": [
                1598653419543486464
            ],
            "id": 1598653419543486464,
            "text": "いちご青汁ラテ……ってなるけど、最近の青汁って苦味を抑えるように作られてるから、「不味い！もう一杯！！」みたいなのはないと思う……&gt;RT"
        },
        {
            "edit_history_tweet_ids": [
                1598653404481744898
            ],
            "id": 1598653404481744898,
            "text": "トレンドのいちご青汁ラテって？？と思ったら、次の茶屋ですか。\n私、まだ今回の後半の肥前くん来てないんだよね。終わるまでに肥前くんの内番クリアファイル来るかなぁ。"
        },
        {
            "edit_history_tweet_ids": [
                1598653353323819011
            ],
            "id": 1598653353323819011,
            "text": "トレンドの”いちご青汁ラテ”、\nえ、何いちごラテなの？青汁なの？と謎すぎて\n見てみたらこれの事ね…\n\nというか、これは美味しいのか…？ https://t.co/K94FvHERts"
        },
        {
            "edit_history_tweet_ids": [
                1598653340379803649
            ],
            "id": 1598653340379803649,
            "text": "いちご青汁ラテって新手の健康食品かと思ったら、豊前江のドリンクで吹き散らかしているｗｗｗ小狐の『お揚げを添えて』はおいしかったです。"
        },
        {
            "edit_history_tweet_ids": [
                1598653332452937728
            ],
            "id": 1598653332452937728,
            "text": "いちご青汁ラテってどんな味ですか豊前さん\nうめぇっちゃ！！ってあの眩しい笑顔で言うんですか"
        },
        {
            "edit_history_tweet_ids": [
                1598653292032458753
            ],
            "id": 1598653292032458753,
            "text": "いちご青汁ラテまじか"
        },
        {
            "edit_history_tweet_ids": [
                1598653171773345794
            ],
            "id": 1598653171773345794,
            "text": "おすすめトレンドのいちご青汁ラテってなんだそのドリンクバーでふざけて作ったカオスな飲み物的なやつは……と思ったらお前か彼氏の擬人化"
        },
        {
            "edit_history_tweet_ids": [
                1598653144355209217
            ],
            "id": 1598653144355209217,
            "text": "いちご青汁ラテ、診断メーカーとかのランダム組み合わせか？って思ったら刀ミュコラボの豊前江のドリンクだったんだけど、えっ、いやえっ？？何……なんだコレ……ちょっと理解に時間を頂いても……？"
        },
        {
            "edit_history_tweet_ids": [
                1598653130149097478
            ],
            "id": 1598653130149097478,
            "text": "ついったくんで面白いもの見つけてたから子供に見せようと思って🔍に行ったらトレンドにいちご青汁ラテってパワーワード見つけてなんだこれってそこから刀剣さんのコラボメニューみて笑ってたら何見せたかったか忘れた🙄"
        },
        {
            "edit_history_tweet_ids": [
                1598653105411096576
            ],
            "id": 1598653105411096576,
            "text": "RT @fuhihinohito: 殺伐としたTLにいちご青汁ラテが https://t.co/kp8XBrV60D"
        },
        {
            "edit_history_tweet_ids": [
                1598652979972046848
            ],
            "id": 1598652979972046848,
            "text": "いちご青汁ラテ。豆乳じゃなく牛乳使用なら飲める。飲んでみたい。"
        },
        {
            "edit_history_tweet_ids": [
                1598652916130516992
            ],
            "id": 1598652916130516992,
            "text": "いちご青汁ラテってトレンドみてスタバ新作かな？とおもたらぶぜんご......🤔"
        },
        {
            "edit_history_tweet_ids": [
                1598652909155405824
            ],
            "id": 1598652909155405824,
            "text": "RT @_mochi2_mochi: トレンドの『いちご青汁ラテ』(豊前江)\n\nえー、と思ったけど子供向けで存在している。混ぜればコレって事で良いのかな… https://t.co/PlZdXGhNNx"
        },
        {
            "edit_history_tweet_ids": [
                1598652906261348352
            ],
            "id": 1598652906261348352,
            "text": "いちご青汁ラテとかいうトンチキ料理何…？って見て震源地がミュ豊前だった時の顔"
        },
        {
            "edit_history_tweet_ids": [
                1598652830277304326
            ],
            "id": 1598652830277304326,
            "text": "いちご……青汁……ラテ……だと⁉️"
        },
        {
            "edit_history_tweet_ids": [
                1598652791710416902
            ],
            "id": 1598652791710416902,
            "text": "いちご青汁ラテがトレンドにあってドリンク同士の話題が混ざり合ったのかな😄と辿ったらガチでそんなドリンクを出す刀剣茶屋…😳 https://t.co/LFw9xkAPuC"
        },
        {
            "edit_history_tweet_ids": [
                1598652787533164544
            ],
            "id": 1598652787533164544,
            "text": "トレンドのいちご青汁ラテこれか🍓"
        }
    ]
}